gemseo_bilevel_outer_approximation/__init__.py
gemseo_bilevel_outer_approximation/algos/__init__.py
gemseo_bilevel_outer_approximation/algos/hypersphere_penalization.py
gemseo_bilevel_outer_approximation/algos/convexification/__init__.py
gemseo_bilevel_outer_approximation/algos/convexification/convexification_correction.py
gemseo_bilevel_outer_approximation/algos/convexification/convexification_discipline.py
gemseo_bilevel_outer_approximation/algos/design_space/__init__.py
gemseo_bilevel_outer_approximation/algos/design_space/catalogue_design_space.py
gemseo_bilevel_outer_approximation/algos/design_space/discrete_catalogue_converter.py
gemseo_bilevel_outer_approximation/algos/opt/__init__.py
gemseo_bilevel_outer_approximation/algos/opt/bilevel_master_outer_approximation/__init__.py
gemseo_bilevel_outer_approximation/algos/opt/bilevel_master_outer_approximation/bilevel_master_outer_approximation.py
gemseo_bilevel_outer_approximation/algos/opt/bilevel_master_outer_approximation/bilevel_master_outer_approximation_settings.py
gemseo_bilevel_outer_approximation/algos/opt/core/__init__.py
gemseo_bilevel_outer_approximation/algos/opt/core/bilevel_outer_approximation.py
gemseo_bilevel_outer_approximation/algos/opt/core/filter_dict_for_settings.py
gemseo_bilevel_outer_approximation/algos/opt/core/outer_approximation_optimizer.py
gemseo_bilevel_outer_approximation/algos/opt/ortools_milp/__init__.py
gemseo_bilevel_outer_approximation/algos/opt/ortools_milp/ortools_milp.py
gemseo_bilevel_outer_approximation/algos/opt/ortools_milp/ortools_milp_settings.py
gemseo_bilevel_outer_approximation/algos/opt/outer_approximation/__init__.py
gemseo_bilevel_outer_approximation/algos/opt/outer_approximation/outer_approximation.py
gemseo_bilevel_outer_approximation/algos/opt/outer_approximation/outer_approximation_settings.py
gemseo_bilevel_outer_approximation/algos/opt/scipy_milp/__init__.py
gemseo_bilevel_outer_approximation/algos/opt/scipy_milp/extended_scipy_milp.py
gemseo_bilevel_outer_approximation-0.1.1.dist-info/licenses/LICENSE.txt
gemseo_bilevel_outer_approximation-0.1.1.dist-info/METADATA
gemseo_bilevel_outer_approximation-0.1.1.dist-info/WHEEL
gemseo_bilevel_outer_approximation-0.1.1.dist-info/entry_points.txt
gemseo_bilevel_outer_approximation-0.1.1.dist-info/top_level.txt
gemseo_bilevel_outer_approximation-0.1.1.dist-info/RECORD
